eflips/depot/__init__.py
eflips/depot/api/__init__.py
eflips/depot/api/defaults/default_settings.json
eflips/depot/api/private/__init__.py
eflips/depot/api/private/consumption.py
eflips/depot/api/private/depot.py
eflips/depot/api/private/results_to_database.py
eflips/depot/api/private/util.py
eflips/depot/configuration.py
eflips/depot/depot.py
eflips/depot/evaluation.py
eflips/depot/filters.py
eflips/depot/input_epex_power_price.py
eflips/depot/layout_opt/__init__.py
eflips/depot/layout_opt/doc/__init__.py
eflips/depot/layout_opt/doc/direct_details.pdf
eflips/depot/layout_opt/evaluation.py
eflips/depot/layout_opt/opt_tools/__init__.py
eflips/depot/layout_opt/opt_tools/crossover.py
eflips/depot/layout_opt/opt_tools/fitness_c_urfd.py
eflips/depot/layout_opt/opt_tools/fitness_util.py
eflips/depot/layout_opt/opt_tools/init.py
eflips/depot/layout_opt/opt_tools/mutation.py
eflips/depot/layout_opt/optimize_c_urfd.py
eflips/depot/layout_opt/packing.py
eflips/depot/layout_opt/settings.py
eflips/depot/layout_opt/template_creation.py
eflips/depot/layout_opt/util.py
eflips/depot/plots.py
eflips/depot/processes.py
eflips/depot/rating.py
eflips/depot/resources.py
eflips/depot/settings_config.py
eflips/depot/simple_vehicle.py
eflips/depot/simulation.py
eflips/depot/smart_charging.py
eflips/depot/standalone.py
eflips/depot/validation.py
eflips_depot-4.15.11.dist-info/METADATA
eflips_depot-4.15.11.dist-info/WHEEL
eflips_depot-4.15.11.dist-info/licenses/LICENSE.md
eflips_depot-4.15.11.dist-info/RECORD
