Metadata-Version: 2.4
Name: eflips-depot
Version: 4.15.11
Summary: Depot Simulation for eFLIPS
License: AGPL-3.0-or-later
License-File: LICENSE.md
Author: Enrico Lauth
Author-email: enrico.lauth@tu-berlin.de
Requires-Python: >=3.11,<3.14
Classifier: License :: OSI Approved :: GNU Affero General Public License v3 or later (AGPLv3+)
Classifier: Programming Language :: Python :: 3
Classifier: Programming Language :: Python :: 3.11
Classifier: Programming Language :: Python :: 3.12
Classifier: Programming Language :: Python :: 3.13
Requires-Dist: eflips (>=0.1.3,<0.2.0)
Requires-Dist: eflips-model (>=10.0.0,<11.0.0)
Requires-Dist: eflips-opt (>=0.3.6,<0.4.0)
Requires-Dist: pandas (>=2.2.0,<3.0.0)
Requires-Dist: scipy (>=1.14.0,<2.0.0)
Requires-Dist: simpy (>=4.0.1,<5.0.0)
Requires-Dist: tqdm (>=4.67.0,<5.0.0)
Requires-Dist: xlrd (<=1.2.0)
Requires-Dist: xlsxwriter (>=3.1.9,<4.0.0)
Project-URL: Homepage, https://github.com/mpm-tu-berlin/eflips-depot
Project-URL: Repository, https://github.com/mpm-tu-berlin/eflips-depot
